{"content":"{\"games\":[{\"creatorId\":60596019,\"creatorName\":\"Wolfpaq\",\"creatorType\":\"User\",\"totalUpVotes\":862544,\"totalDownVotes\":89500,\"universeId\":1686885941,\"name\":\"Brookhaven 🏡RP\",\"placeId\":4924922222,\"playerCount\":463074,\"imageToken\":\"T_4924922222_4cda\",\"isSponsored\":false,\"nativeAdData\":\"\",\"isShowSponsoredLabel\":false,\"price\":null,\"analyticsIdentifier\":null,\"gameDescription\":null},{\"creatorId\":295182,\"creatorName\":\"DreamCraft\",\"creatorType\":\"Group\",\"totalUpVotes\":3956417,\"totalDownVotes\":717198,\"universeId\":383310974,\"name\":\"Adopt Me!\",\"placeId\":920587237,\"playerCount\":262425,\"imageToken\":\"T_920587237_6b7b\",\"isSponsored\":false,\"nativeAdData\":\"\",\"isShowSponsoredLabel\":false,\"price\":null,\"analyticsIdentifier\":null,\"gameDescription\":null},{\"creatorId\":63700903,\"creatorName\":\"Coeptus\",\"creatorType\":\"User\",\"totalUpVotes\":3117357,\"totalDownVotes\":265623,\"universeId\":88070565,\"name\":\"Welcome to Bloxburg\",\"placeId\":185655149,\"playerCount\":91305,\"imageToken\":\"T_185655149_9e67\",\"isSponsored\":false,\"nativeAdData\":\"\",\"isShowSponsoredLabel\":false,\"price\":25,\"analyticsIdentifier\":null,\"gameDescription\":null},{\"creatorId\":4372130,\"creatorName\":\"go play eclipsis\",\"creatorType\":\"Group\",\"totalUpVotes\":519161,\"totalDownVotes\":42154,\"universeId\":994732206,\"name\":\"[UPDATE 14] Blox Fruits\",\"placeId\":2753915549,\"playerCount\":65693,\"imageToken\":\"T_2753915549_8271\",\"isSponsored\":false,\"nativeAdData\":\"\",\"isShowSponsoredLabel\":false,\"price\":null,\"analyticsIdentifier\":null,\"gameDescription\":null},{\"creatorId\":2613928,\"creatorName\":\"ROLVe Community\",\"creatorType\":\"Group\",\"totalUpVotes\":2615376,\"totalDownVotes\":347588,\"universeId\":111958650,\"name\":\"Arsenal\",\"placeId\":286090429,\"playerCount\":45995,\"imageToken\":\"T_286090429_76fe\",\"isSponsored\":false,\"nativeAdData\":\"\",\"isShowSponsoredLabel\":false,\"price\":null,\"analyticsIdentifier\":null,\"gameDescription\":null},{\"creatorId\":1848960,\"creatorName\":\"Nikilis\",\"creatorType\":\"User\",\"totalUpVotes\":3600044,\"totalDownVotes\":295183,\"universeId\":66654135,\"name\":\"Murder Mystery 2\",\"placeId\":142823291,\"playerCount\":74030,\"imageToken\":\"T_142823291_8b7a\",\"isSponsored\":false,\"nativeAdData\":\"\",\"isShowSponsoredLabel\":false,\"price\":null,\"analyticsIdentifier\":null,\"gameDescription\":null},{\"creatorId\":5449496,\"creatorName\":\"Lyte Interactive\",\"creatorType\":\"Group\",\"totalUpVotes\":176672,\"totalDownVotes\":19906,\"universeId\":2404080894,\"name\":\"[HEX] Funky Friday\",\"placeId\":6447798030,\"playerCount\":40893,\"imageToken\":\"T_6447798030_4d91\",\"isSponsored\":false,\"nativeAdData\":\"\",\"isShowSponsoredLabel\":false,\"price\":null,\"analyticsIdentifier\":null,\"gameDescription\":null},{\"creatorId\":29622,\"creatorName\":\"callmehbob\",\"creatorType\":\"User\",\"totalUpVotes\":2008983,\"totalDownVotes\":275248,\"universeId\":321778215,\"name\":\"Royale🌈High\",\"placeId\":735030788,\"playerCount\":60522,\"imageToken\":\"T_735030788_21f6\",\"isSponsored\":false,\"nativeAdData\":\"\",\"isShowSponsoredLabel\":false,\"price\":null,\"analyticsIdentifier\":null,\"gameDescription\":null},{\"creatorId\":5202664,\"creatorName\":\"BlockZone\",\"creatorType\":\"Group\",\"totalUpVotes\":927852,\"totalDownVotes\":47347,\"universeId\":1348402608,\"name\":\"DIMENSION 5⛩️ Anime Fighting Simulator\",\"placeId\":4042427666,\"playerCount\":38953,\"imageToken\":\"T_4042427666_fd51\",\"isSponsored\":false,\"nativeAdData\":\"\",\"isShowSponsoredLabel\":false,\"price\":null,\"analyticsIdentifier\":null,\"gameDescription\":null},{\"creatorId\":123247,\"creatorName\":\"alexnewtron\",\"creatorType\":\"User\",\"totalUpVotes\":2135164,\"totalDownVotes\":292853,\"universeId\":140239261,\"name\":\"💙 MeepCity 💙\",\"placeId\":370731277,\"playerCount\":93906,\"imageToken\":\"T_370731277_ebb7\",\"isSponsored\":false,\"nativeAdData\":\"\",\"isShowSponsoredLabel\":false,\"price\":null,\"analyticsIdentifier\":null,\"gameDescription\":null},{\"creatorId\":1226491,\"creatorName\":\"RELL World\",\"creatorType\":\"Group\",\"totalUpVotes\":837732,\"totalDownVotes\":53312,\"universeId\":1511883870,\"name\":\"Shindo\",\"placeId\":4616652839,\"playerCount\":33084,\"imageToken\":\"T_4616652839_4a58\",\"isSponsored\":false,\"nativeAdData\":\"\",\"isShowSponsoredLabel\":false,\"price\":null,\"analyticsIdentifier\":null,\"gameDescription\":null},{\"creatorId\":9277770,\"creatorName\":\"Anime Legend Studios\",\"creatorType\":\"Group\",\"totalUpVotes\":51314,\"totalDownVotes\":4107,\"universeId\":2317140681,\"name\":\"[ONE PIECE UPDATE] Anime Mania\",\"placeId\":6284881984,\"playerCount\":28467,\"imageToken\":\"T_6284881984_34ef\",\"isSponsored\":false,\"nativeAdData\":\"\",\"isShowSponsoredLabel\":false,\"price\":null,\"analyticsIdentifier\":null,\"gameDescription\":null},{\"creatorId\":3194064,\"creatorName\":\"Bizarre Studios®\",\"creatorType\":\"Group\",\"totalUpVotes\":192590,\"totalDownVotes\":29211,\"universeId\":1016936714,\"name\":\"(TA4 & SCR REWORK) Your Bizarre Adventure \",\"placeId\":2809202155,\"playerCount\":20113,\"imageToken\":\"T_2809202155_cd90\",\"isSponsored\":false,\"nativeAdData\":\"\",\"isShowSponsoredLabel\":false,\"price\":null,\"analyticsIdentifier\":null,\"gameDescription\":null},{\"creatorId\":4217910,\"creatorName\":\"YXCeptional Studios\",\"creatorType\":\"Group\",\"totalUpVotes\":2000501,\"totalDownVotes\":624788,\"universeId\":703124385,\"name\":\"Tower of Hell\",\"placeId\":1962086868,\"playerCount\":66447,\"imageToken\":\"T_1962086868_5fcb\",\"isSponsored\":false,\"nativeAdData\":\"\",\"isShowSponsoredLabel\":false,\"price\":null,\"analyticsIdentifier\":null,\"gameDescription\":null},{\"creatorId\":3059674,\"creatorName\":\"Badimo\",\"creatorType\":\"Group\",\"totalUpVotes\":4286261,\"totalDownVotes\":579607,\"universeId\":245662005,\"name\":\"Jailbreak\",\"placeId\":606849621,\"playerCount\":31915,\"imageToken\":\"T_606849621_25a8\",\"isSponsored\":false,\"nativeAdData\":\"\",\"isShowSponsoredLabel\":false,\"price\":null,\"analyticsIdentifier\":null,\"gameDescription\":null},{\"creatorId\":5292947,\"creatorName\":\"Top Down Games\",\"creatorType\":\"Group\",\"totalUpVotes\":478251,\"totalDownVotes\":32748,\"universeId\":1720936166,\"name\":\"All Star Tower Defense\",\"placeId\":4996049426,\"playerCount\":26586,\"imageToken\":\"T_4996049426_1b09\",\"isSponsored\":false,\"nativeAdData\":\"\",\"isShowSponsoredLabel\":false,\"price\":null,\"analyticsIdentifier\":null,\"gameDescription\":null},{\"creatorId\":2782840,\"creatorName\":\"Chillz Studios\",\"creatorType\":\"Group\",\"totalUpVotes\":1338599,\"totalDownVotes\":114289,\"universeId\":210851291,\"name\":\"Build A Boat For Treasure\",\"placeId\":537413528,\"playerCount\":32272,\"imageToken\":\"T_537413528_d6fc\",\"isSponsored\":false,\"nativeAdData\":\"\",\"isShowSponsoredLabel\":false,\"price\":null,\"analyticsIdentifier\":null,\"gameDescription\":null},{\"creatorId\":6042520,\"creatorName\":\"Grandma's Favourite Games\",\"creatorType\":\"Group\",\"totalUpVotes\":80881,\"totalDownVotes\":6937,\"universeId\":2033913602,\"name\":\"Mall Tycoon\",\"placeId\":5736409216,\"playerCount\":36367,\"imageToken\":\"T_5736409216_bc91\",\"isSponsored\":false,\"nativeAdData\":\"\",\"isShowSponsoredLabel\":false,\"price\":null,\"analyticsIdentifier\":null,\"gameDescription\":null},{\"creatorId\":3333298,\"creatorName\":\"Rumble Studios\",\"creatorType\":\"Group\",\"totalUpVotes\":891240,\"totalDownVotes\":115408,\"universeId\":892043755,\"name\":\"[🍀SILVER + LUCK  🍀] Bubble Gum Simulator\",\"placeId\":2512643572,\"playerCount\":17218,\"imageToken\":\"T_2512643572_64e\",\"isSponsored\":false,\"nativeAdData\":\"\",\"isShowSponsoredLabel\":false,\"price\":null,\"analyticsIdentifier\":null,\"gameDescription\":null},{\"creatorId\":1912490,\"creatorName\":\"Onett\",\"creatorType\":\"User\",\"totalUpVotes\":1154698,\"totalDownVotes\":66229,\"universeId\":601130232,\"name\":\"Bee Swarm Simulator\",\"placeId\":1537690962,\"playerCount\":21583,\"imageToken\":\"T_1537690962_a8c9\",\"isSponsored\":false,\"nativeAdData\":\"\",\"isShowSponsoredLabel\":false,\"price\":null,\"analyticsIdentifier\":null,\"gameDescription\":null},{\"creatorId\":5774246,\"creatorName\":\"Easy.gg\",\"creatorType\":\"Group\",\"totalUpVotes\":660021,\"totalDownVotes\":91408,\"universeId\":1659645941,\"name\":\"Islands 👑 [GODZILLA VS KONG!]\",\"placeId\":4872321990,\"playerCount\":19394,\"imageToken\":\"T_4872321990_db87\",\"isSponsored\":false,\"nativeAdData\":\"\",\"isShowSponsoredLabel\":false,\"price\":null,\"analyticsIdentifier\":null,\"gameDescription\":null},{\"creatorId\":21823494,\"creatorName\":\"MiniToon\",\"creatorType\":\"User\",\"totalUpVotes\":2215965,\"totalDownVotes\":229893,\"universeId\":1516533665,\"name\":\"Piggy [BOOK 2] CHAPTER 6!\",\"placeId\":4623386862,\"playerCount\":45395,\"imageToken\":\"T_4623386862_d990\",\"isSponsored\":false,\"nativeAdData\":\"\",\"isShowSponsoredLabel\":false,\"price\":null,\"analyticsIdentifier\":null,\"gameDescription\":null},{\"creatorId\":3250407,\"creatorName\":\"Block Evolution Studios\",\"creatorType\":\"Group\",\"totalUpVotes\":199508,\"totalDownVotes\":21832,\"universeId\":1230230722,\"name\":\"🧒👦 KIDS UPDATE! Club Roblox\",\"placeId\":3457390032,\"playerCount\":40939,\"imageToken\":\"T_3457390032_bedf\",\"isSponsored\":false,\"nativeAdData\":\"\",\"isShowSponsoredLabel\":false,\"price\":null,\"analyticsIdentifier\":null,\"gameDescription\":null},{\"creatorId\":1103278,\"creatorName\":\"StyLiS Studios\",\"creatorType\":\"Group\",\"totalUpVotes\":1754142,\"totalDownVotes\":136114,\"universeId\":113491250,\"name\":\"Phantom Forces\",\"placeId\":292439477,\"playerCount\":9287,\"imageToken\":\"T_292439477_68f7\",\"isSponsored\":false,\"nativeAdData\":\"\",\"isShowSponsoredLabel\":false,\"price\":null,\"analyticsIdentifier\":null,\"gameDescription\":null},{\"creatorId\":4698921,\"creatorName\":\"Da Hood Entertainment\",\"creatorType\":\"Group\",\"totalUpVotes\":236020,\"totalDownVotes\":128022,\"universeId\":1008451066,\"name\":\"Da Hood\",\"placeId\":2788229376,\"playerCount\":18564,\"imageToken\":\"T_2788229376_aeaa\",\"isSponsored\":false,\"nativeAdData\":\"\",\"isShowSponsoredLabel\":false,\"price\":null,\"analyticsIdentifier\":null,\"gameDescription\":null},{\"creatorId\":3735330,\"creatorName\":\"Dogs Studios: South\",\"creatorType\":\"Group\",\"totalUpVotes\":168981,\"totalDownVotes\":27509,\"universeId\":578392296,\"name\":\"[ GOJO & HIEI ] Anime Battle Arena \",\"placeId\":1458767429,\"playerCount\":9467,\"imageToken\":\"T_1458767429_6114\",\"isSponsored\":false,\"nativeAdData\":\"\",\"isShowSponsoredLabel\":false,\"price\":null,\"analyticsIdentifier\":null,\"gameDescription\":null},{\"creatorId\":5348890,\"creatorName\":\"Thai Piece\",\"creatorType\":\"Group\",\"totalUpVotes\":153898,\"totalDownVotes\":15775,\"universeId\":1451439645,\"name\":\"[Second Sea] King Piece 🌊\",\"placeId\":4520749081,\"playerCount\":17615,\"imageToken\":\"T_4520749081_db05\",\"isSponsored\":false,\"nativeAdData\":\"\",\"isShowSponsoredLabel\":false,\"price\":null,\"analyticsIdentifier\":null,\"gameDescription\":null},{\"creatorId\":49689731,\"creatorName\":\"MaplGalaxy\",\"creatorType\":\"User\",\"totalUpVotes\":255693,\"totalDownVotes\":23603,\"universeId\":2387288336,\"name\":\"Basically FNF\",\"placeId\":6417009050,\"playerCount\":19242,\"imageToken\":\"T_6417009050_b437\",\"isSponsored\":false,\"nativeAdData\":\"\",\"isShowSponsoredLabel\":false,\"price\":null,\"analyticsIdentifier\":null,\"gameDescription\":null},{\"creatorId\":3229308,\"creatorName\":\"Grand Quest Games\",\"creatorType\":\"Group\",\"totalUpVotes\":109996,\"totalDownVotes\":6218,\"universeId\":648454481,\"name\":\"[2X LOGIA ❤️VALENTINE EVENT]Grand Piece Online\",\"placeId\":1730877806,\"playerCount\":7304,\"imageToken\":\"T_1730877806_428d\",\"isSponsored\":false,\"nativeAdData\":\"\",\"isShowSponsoredLabel\":false,\"price\":200,\"analyticsIdentifier\":null,\"gameDescription\":null},{\"creatorId\":1730435200,\"creatorName\":\"SnowdustDev\",\"creatorType\":\"User\",\"totalUpVotes\":134327,\"totalDownVotes\":60928,\"universeId\":1852226622,\"name\":\"Gacha Online| Custom OC RP⭐ (Roleplay)\",\"placeId\":5289509545,\"playerCount\":27132,\"imageToken\":\"T_5289509545_1eec\",\"isSponsored\":false,\"nativeAdData\":\"\",\"isShowSponsoredLabel\":false,\"price\":null,\"analyticsIdentifier\":null,\"gameDescription\":null},{\"creatorId\":2613928,\"creatorName\":\"ROLVe Community\",\"creatorType\":\"Group\",\"totalUpVotes\":639801,\"totalDownVotes\":124163,\"universeId\":115797356,\"name\":\"Counter Blox\",\"placeId\":301549746,\"playerCount\":5256,\"imageToken\":\"T_301549746_2abf\",\"isSponsored\":false,\"nativeAdData\":\"\",\"isShowSponsoredLabel\":false,\"price\":null,\"analyticsIdentifier\":null,\"gameDescription\":null},{\"creatorId\":6258143,\"creatorName\":\"Wonder Works Studio\",\"creatorType\":\"Group\",\"totalUpVotes\":262882,\"totalDownVotes\":43492,\"universeId\":1751969566,\"name\":\"[Egg Hunt]🐰Overlook Bay!\",\"placeId\":5063122755,\"playerCount\":16148,\"imageToken\":\"T_5063122755_b37a\",\"isSponsored\":false,\"nativeAdData\":\"\",\"isShowSponsoredLabel\":false,\"price\":null,\"analyticsIdentifier\":null,\"gameDescription\":null},{\"creatorId\":22653509,\"creatorName\":\"mr_beanGuy\",\"creatorType\":\"User\",\"totalUpVotes\":706240,\"totalDownVotes\":105282,\"universeId\":719754874,\"name\":\"Ragdoll Engine\",\"placeId\":2041312716,\"playerCount\":18208,\"imageToken\":\"T_2041312716_3f7c\",\"isSponsored\":false,\"nativeAdData\":\"\",\"isShowSponsoredLabel\":false,\"price\":null,\"analyticsIdentifier\":null,\"gameDescription\":null},{\"creatorId\":3642592,\"creatorName\":\"Schwifty Studios\",\"creatorType\":\"Group\",\"totalUpVotes\":1252884,\"totalDownVotes\":272079,\"universeId\":498490399,\"name\":\"Mad City\",\"placeId\":1224212277,\"playerCount\":8796,\"imageToken\":\"T_1224212277_2d87\",\"isSponsored\":false,\"nativeAdData\":\"\",\"isShowSponsoredLabel\":false,\"price\":null,\"analyticsIdentifier\":null,\"gameDescription\":null},{\"creatorId\":7312028,\"creatorName\":\"Simple Games Incorporated\",\"creatorType\":\"Group\",\"totalUpVotes\":34344,\"totalDownVotes\":6448,\"universeId\":1995935886,\"name\":\" [Perks!] Gods Of Glory\",\"placeId\":5665787539,\"playerCount\":12811,\"imageToken\":\"T_5665787539_1541\",\"isSponsored\":false,\"nativeAdData\":\"\",\"isShowSponsoredLabel\":false,\"price\":null,\"analyticsIdentifier\":null,\"gameDescription\":null},{\"creatorId\":3755133,\"creatorName\":\"Starboard Studios\",\"creatorType\":\"Group\",\"totalUpVotes\":285111,\"totalDownVotes\":45329,\"universeId\":807930589,\"name\":\"The Wild West\",\"placeId\":2317712696,\"playerCount\":4412,\"imageToken\":\"T_2317712696_5f50\",\"isSponsored\":false,\"nativeAdData\":\"\",\"isShowSponsoredLabel\":false,\"price\":null,\"analyticsIdentifier\":null,\"gameDescription\":null},{\"creatorId\":28603491,\"creatorName\":\"SushiWalrus\",\"creatorType\":\"User\",\"totalUpVotes\":544260,\"totalDownVotes\":56496,\"universeId\":380704901,\"name\":\"[PS ADMIN!] Ro-Ghoul [ALPHA]\",\"placeId\":914010731,\"playerCount\":4406,\"imageToken\":\"T_914010731_9b0a\",\"isSponsored\":false,\"nativeAdData\":\"\",\"isShowSponsoredLabel\":false,\"price\":null,\"analyticsIdentifier\":null,\"gameDescription\":null},{\"creatorId\":3182154,\"creatorName\":\"A.W. Apps\",\"creatorType\":\"Group\",\"totalUpVotes\":1460500,\"totalDownVotes\":115587,\"universeId\":372226183,\"name\":\"Flee the Facility [Beta]\",\"placeId\":893973440,\"playerCount\":18294,\"imageToken\":\"T_893973440_9c11\",\"isSponsored\":false,\"nativeAdData\":\"\",\"isShowSponsoredLabel\":false,\"price\":null,\"analyticsIdentifier\":null,\"gameDescription\":null},{\"creatorId\":4914494,\"creatorName\":\"Paradoxum Games\",\"creatorType\":\"Group\",\"totalUpVotes\":488614,\"totalDownVotes\":40682,\"universeId\":1176784616,\"name\":\"🏆Tower Defense Simulator🏆\",\"placeId\":3260590327,\"playerCount\":8426,\"imageToken\":\"T_3260590327_d762\",\"isSponsored\":false,\"nativeAdData\":\"\",\"isShowSponsoredLabel\":false,\"price\":null,\"analyticsIdentifier\":null,\"gameDescription\":null},{\"creatorId\":4570453,\"creatorName\":\"One Piece Millennium\",\"creatorType\":\"Group\",\"totalUpVotes\":22257,\"totalDownVotes\":3351,\"universeId\":2076312981,\"name\":\"[Alpha] One Piece: Millennium 3\",\"placeId\":5835263912,\"playerCount\":5576,\"imageToken\":\"T_5835263912_252\",\"isSponsored\":false,\"nativeAdData\":\"\",\"isShowSponsoredLabel\":false,\"price\":null,\"analyticsIdentifier\":null,\"gameDescription\":null}],\"suggestedKeyword\":null,\"correctedKeyword\":null,\"filteredKeyword\":null,\"hasMoreRows\":true,\"nextPageExclusiveStartId\":null,\"featuredSearchUniverseId\":null,\"emphasis\":false,\"cutOffIndex\":null,\"algorithm\":\"GameSearchUsingSimilarQueryService\",\"algorithmQueryType\":\"Bucketboost\",\"suggestionAlgorithm\":\"GameSuggestions_V2\",\"relatedGames\":[]}"}