{"content":"{\"games\":[{\"creatorId\":295182,\"creatorName\":\"DreamCraft\",\"creatorType\":\"Group\",\"totalUpVotes\":3959850,\"totalDownVotes\":717962,\"universeId\":383310974,\"name\":\"Adopt Me!\",\"placeId\":920587237,\"playerCount\":402626,\"imageToken\":\"T_920587237_6b7b\",\"isSponsored\":false,\"nativeAdData\":\"\",\"isShowSponsoredLabel\":false,\"price\":null,\"analyticsIdentifier\":null,\"gameDescription\":null},{\"creatorId\":60596019,\"creatorName\":\"Wolfpaq\",\"creatorType\":\"User\",\"totalUpVotes\":866854,\"totalDownVotes\":89982,\"universeId\":1686885941,\"name\":\"Brookhaven 🏡RP\",\"placeId\":4924922222,\"playerCount\":545174,\"imageToken\":\"T_4924922222_4cda\",\"isSponsored\":false,\"nativeAdData\":\"\",\"isShowSponsoredLabel\":false,\"price\":null,\"analyticsIdentifier\":null,\"gameDescription\":null},{\"creatorId\":4372130,\"creatorName\":\"go play eclipsis\",\"creatorType\":\"Group\",\"totalUpVotes\":520811,\"totalDownVotes\":42258,\"universeId\":994732206,\"name\":\"[UPDATE 14] Blox Fruits\",\"placeId\":2753915549,\"playerCount\":95811,\"imageToken\":\"T_2753915549_8271\",\"isSponsored\":false,\"nativeAdData\":\"\",\"isShowSponsoredLabel\":false,\"price\":null,\"analyticsIdentifier\":null,\"gameDescription\":null},{\"creatorId\":1848960,\"creatorName\":\"Nikilis\",\"creatorType\":\"User\",\"totalUpVotes\":3602636,\"totalDownVotes\":295460,\"universeId\":66654135,\"name\":\"Murder Mystery 2\",\"placeId\":142823291,\"playerCount\":96253,\"imageToken\":\"T_142823291_8b7a\",\"isSponsored\":false,\"nativeAdData\":\"\",\"isShowSponsoredLabel\":false,\"price\":null,\"analyticsIdentifier\":null,\"gameDescription\":null},{\"creatorId\":63700903,\"creatorName\":\"Coeptus\",\"creatorType\":\"User\",\"totalUpVotes\":3119166,\"totalDownVotes\":266032,\"universeId\":88070565,\"name\":\"Welcome to Bloxburg\",\"placeId\":185655149,\"playerCount\":97484,\"imageToken\":\"T_185655149_9e67\",\"isSponsored\":false,\"nativeAdData\":\"\",\"isShowSponsoredLabel\":false,\"price\":25,\"analyticsIdentifier\":null,\"gameDescription\":null},{\"creatorId\":2613928,\"creatorName\":\"ROLVe Community\",\"creatorType\":\"Group\",\"totalUpVotes\":2618316,\"totalDownVotes\":347903,\"universeId\":111958650,\"name\":\"Arsenal\",\"placeId\":286090429,\"playerCount\":49508,\"imageToken\":\"T_286090429_76fe\",\"isSponsored\":false,\"nativeAdData\":\"\",\"isShowSponsoredLabel\":false,\"price\":null,\"analyticsIdentifier\":null,\"gameDescription\":null},{\"creatorId\":5202664,\"creatorName\":\"BlockZone\",\"creatorType\":\"Group\",\"totalUpVotes\":929261,\"totalDownVotes\":47391,\"universeId\":1348402608,\"name\":\"DIMENSION 5⛩️ Anime Fighting Simulator\",\"placeId\":4042427666,\"playerCount\":50297,\"imageToken\":\"T_4042427666_fd51\",\"isSponsored\":false,\"nativeAdData\":\"\",\"isShowSponsoredLabel\":false,\"price\":null,\"analyticsIdentifier\":null,\"gameDescription\":null},{\"creatorId\":29622,\"creatorName\":\"callmehbob\",\"creatorType\":\"User\",\"totalUpVotes\":2009992,\"totalDownVotes\":275359,\"universeId\":321778215,\"name\":\"Royale🌈High\",\"placeId\":735030788,\"playerCount\":72852,\"imageToken\":\"T_735030788_21f6\",\"isSponsored\":false,\"nativeAdData\":\"\",\"isShowSponsoredLabel\":false,\"price\":null,\"analyticsIdentifier\":null,\"gameDescription\":null},{\"creatorId\":123247,\"creatorName\":\"alexnewtron\",\"creatorType\":\"User\",\"totalUpVotes\":2136211,\"totalDownVotes\":292994,\"universeId\":140239261,\"name\":\"💙 MeepCity 💙\",\"placeId\":370731277,\"playerCount\":104472,\"imageToken\":\"T_370731277_ebb7\",\"isSponsored\":false,\"nativeAdData\":\"\",\"isShowSponsoredLabel\":false,\"price\":null,\"analyticsIdentifier\":null,\"gameDescription\":null},{\"creatorId\":1226491,\"creatorName\":\"RELL World\",\"creatorType\":\"Group\",\"totalUpVotes\":838728,\"totalDownVotes\":53391,\"universeId\":1511883870,\"name\":\"Shindo\",\"placeId\":4616652839,\"playerCount\":35888,\"imageToken\":\"T_4616652839_4a58\",\"isSponsored\":false,\"nativeAdData\":\"\",\"isShowSponsoredLabel\":false,\"price\":null,\"analyticsIdentifier\":null,\"gameDescription\":null},{\"creatorId\":5449496,\"creatorName\":\"Lyte Interactive\",\"creatorType\":\"Group\",\"totalUpVotes\":180982,\"totalDownVotes\":20302,\"universeId\":2404080894,\"name\":\"[HEX] Funky Friday\",\"placeId\":6447798030,\"playerCount\":33962,\"imageToken\":\"T_6447798030_4d91\",\"isSponsored\":false,\"nativeAdData\":\"\",\"isShowSponsoredLabel\":false,\"price\":null,\"analyticsIdentifier\":null,\"gameDescription\":null},{\"creatorId\":4217910,\"creatorName\":\"YXCeptional Studios\",\"creatorType\":\"Group\",\"totalUpVotes\":2002925,\"totalDownVotes\":625502,\"universeId\":703124385,\"name\":\"Tower of Hell\",\"placeId\":1962086868,\"playerCount\":88347,\"imageToken\":\"T_1962086868_5fcb\",\"isSponsored\":false,\"nativeAdData\":\"\",\"isShowSponsoredLabel\":false,\"price\":null,\"analyticsIdentifier\":null,\"gameDescription\":null},{\"creatorId\":3059674,\"creatorName\":\"Badimo\",\"creatorType\":\"Group\",\"totalUpVotes\":4287415,\"totalDownVotes\":579753,\"universeId\":245662005,\"name\":\"Jailbreak\",\"placeId\":606849621,\"playerCount\":40495,\"imageToken\":\"T_606849621_25a8\",\"isSponsored\":false,\"nativeAdData\":\"\",\"isShowSponsoredLabel\":false,\"price\":null,\"analyticsIdentifier\":null,\"gameDescription\":null},{\"creatorId\":3194064,\"creatorName\":\"Bizarre Studios®\",\"creatorType\":\"Group\",\"totalUpVotes\":194621,\"totalDownVotes\":29215,\"universeId\":1016936714,\"name\":\"(TA4 & SCR REWORK) Your Bizarre Adventure \",\"placeId\":2809202155,\"playerCount\":22450,\"imageToken\":\"T_2809202155_cd90\",\"isSponsored\":false,\"nativeAdData\":\"\",\"isShowSponsoredLabel\":false,\"price\":null,\"analyticsIdentifier\":null,\"gameDescription\":null},{\"creatorId\":6042520,\"creatorName\":\"Grandma's Favourite Games\",\"creatorType\":\"Group\",\"totalUpVotes\":83697,\"totalDownVotes\":7110,\"universeId\":2033913602,\"name\":\"Mall Tycoon\",\"placeId\":5736409216,\"playerCount\":56321,\"imageToken\":\"T_5736409216_bc91\",\"isSponsored\":false,\"nativeAdData\":\"\",\"isShowSponsoredLabel\":false,\"price\":null,\"analyticsIdentifier\":null,\"gameDescription\":null},{\"creatorId\":2782840,\"creatorName\":\"Chillz Studios\",\"creatorType\":\"Group\",\"totalUpVotes\":1339842,\"totalDownVotes\":114365,\"universeId\":210851291,\"name\":\"Build A Boat For Treasure\",\"placeId\":537413528,\"playerCount\":44965,\"imageToken\":\"T_537413528_d6fc\",\"isSponsored\":false,\"nativeAdData\":\"\",\"isShowSponsoredLabel\":false,\"price\":null,\"analyticsIdentifier\":null,\"gameDescription\":null},{\"creatorId\":5292947,\"creatorName\":\"Top Down Games\",\"creatorType\":\"Group\",\"totalUpVotes\":478745,\"totalDownVotes\":32794,\"universeId\":1720936166,\"name\":\"All Star Tower Defense\",\"placeId\":4996049426,\"playerCount\":29258,\"imageToken\":\"T_4996049426_1b09\",\"isSponsored\":false,\"nativeAdData\":\"\",\"isShowSponsoredLabel\":false,\"price\":null,\"analyticsIdentifier\":null,\"gameDescription\":null},{\"creatorId\":1912490,\"creatorName\":\"Onett\",\"creatorType\":\"User\",\"totalUpVotes\":1155401,\"totalDownVotes\":66257,\"universeId\":601130232,\"name\":\"Bee Swarm Simulator\",\"placeId\":1537690962,\"playerCount\":32367,\"imageToken\":\"T_1537690962_a8c9\",\"isSponsored\":false,\"nativeAdData\":\"\",\"isShowSponsoredLabel\":false,\"price\":null,\"analyticsIdentifier\":null,\"gameDescription\":null},{\"creatorId\":9277770,\"creatorName\":\"Anime Legend Studios\",\"creatorType\":\"Group\",\"totalUpVotes\":53452,\"totalDownVotes\":4352,\"universeId\":2317140681,\"name\":\"[ONE PIECE UPDATE] Anime Mania\",\"placeId\":6284881984,\"playerCount\":26952,\"imageToken\":\"T_6284881984_34ef\",\"isSponsored\":false,\"nativeAdData\":\"\",\"isShowSponsoredLabel\":false,\"price\":null,\"analyticsIdentifier\":null,\"gameDescription\":null},{\"creatorId\":3333298,\"creatorName\":\"Rumble Studios\",\"creatorType\":\"Group\",\"totalUpVotes\":891598,\"totalDownVotes\":115463,\"universeId\":892043755,\"name\":\"[🍀SILVER + LUCK  🍀] Bubble Gum Simulator\",\"placeId\":2512643572,\"playerCount\":19619,\"imageToken\":\"T_2512643572_64e\",\"isSponsored\":false,\"nativeAdData\":\"\",\"isShowSponsoredLabel\":false,\"price\":null,\"analyticsIdentifier\":null,\"gameDescription\":null},{\"creatorId\":5774246,\"creatorName\":\"Easy.gg\",\"creatorType\":\"Group\",\"totalUpVotes\":660672,\"totalDownVotes\":91493,\"universeId\":1659645941,\"name\":\"Islands 👑 [GODZILLA VS KONG!]\",\"placeId\":4872321990,\"playerCount\":24812,\"imageToken\":\"T_4872321990_db87\",\"isSponsored\":false,\"nativeAdData\":\"\",\"isShowSponsoredLabel\":false,\"price\":null,\"analyticsIdentifier\":null,\"gameDescription\":null},{\"creatorId\":3250407,\"creatorName\":\"Block Evolution Studios\",\"creatorType\":\"Group\",\"totalUpVotes\":200548,\"totalDownVotes\":21907,\"universeId\":1230230722,\"name\":\"🧒👦 KIDS UPDATE! Club Roblox\",\"placeId\":3457390032,\"playerCount\":57097,\"imageToken\":\"T_3457390032_bedf\",\"isSponsored\":false,\"nativeAdData\":\"\",\"isShowSponsoredLabel\":false,\"price\":null,\"analyticsIdentifier\":null,\"gameDescription\":null},{\"creatorId\":21823494,\"creatorName\":\"MiniToon\",\"creatorType\":\"User\",\"totalUpVotes\":2216895,\"totalDownVotes\":230023,\"universeId\":1516533665,\"name\":\"Piggy [BOOK 2] CHAPTER 6!\",\"placeId\":4623386862,\"playerCount\":57208,\"imageToken\":\"T_4623386862_d990\",\"isSponsored\":false,\"nativeAdData\":\"\",\"isShowSponsoredLabel\":false,\"price\":null,\"analyticsIdentifier\":null,\"gameDescription\":null},{\"creatorId\":2613928,\"creatorName\":\"ROLVe Community\",\"creatorType\":\"Group\",\"totalUpVotes\":640165,\"totalDownVotes\":124270,\"universeId\":115797356,\"name\":\"Counter Blox\",\"placeId\":301549746,\"playerCount\":10521,\"imageToken\":\"T_301549746_2abf\",\"isSponsored\":false,\"nativeAdData\":\"\",\"isShowSponsoredLabel\":false,\"price\":null,\"analyticsIdentifier\":null,\"gameDescription\":null},{\"creatorId\":1103278,\"creatorName\":\"StyLiS Studios\",\"creatorType\":\"Group\",\"totalUpVotes\":1754803,\"totalDownVotes\":136178,\"universeId\":113491250,\"name\":\"Phantom Forces\",\"placeId\":292439477,\"playerCount\":9480,\"imageToken\":\"T_292439477_68f7\",\"isSponsored\":false,\"nativeAdData\":\"\",\"isShowSponsoredLabel\":false,\"price\":null,\"analyticsIdentifier\":null,\"gameDescription\":null},{\"creatorId\":5348890,\"creatorName\":\"Thai Piece\",\"creatorType\":\"Group\",\"totalUpVotes\":154496,\"totalDownVotes\":15829,\"universeId\":1451439645,\"name\":\"[Second Sea] King Piece 🌊\",\"placeId\":4520749081,\"playerCount\":20549,\"imageToken\":\"T_4520749081_db05\",\"isSponsored\":false,\"nativeAdData\":\"\",\"isShowSponsoredLabel\":false,\"price\":null,\"analyticsIdentifier\":null,\"gameDescription\":null},{\"creatorId\":3642592,\"creatorName\":\"Schwifty Studios\",\"creatorType\":\"Group\",\"totalUpVotes\":1253392,\"totalDownVotes\":272176,\"universeId\":498490399,\"name\":\"Mad City\",\"placeId\":1224212277,\"playerCount\":15721,\"imageToken\":\"T_1224212277_2d87\",\"isSponsored\":false,\"nativeAdData\":\"\",\"isShowSponsoredLabel\":false,\"price\":null,\"analyticsIdentifier\":null,\"gameDescription\":null},{\"creatorId\":3735330,\"creatorName\":\"Dogs Studios: South\",\"creatorType\":\"Group\",\"totalUpVotes\":169366,\"totalDownVotes\":27598,\"universeId\":578392296,\"name\":\"[ GOJO & HIEI ] Anime Battle Arena \",\"placeId\":1458767429,\"playerCount\":8343,\"imageToken\":\"T_1458767429_6114\",\"isSponsored\":false,\"nativeAdData\":\"\",\"isShowSponsoredLabel\":false,\"price\":null,\"analyticsIdentifier\":null,\"gameDescription\":null},{\"creatorId\":49689731,\"creatorName\":\"MaplGalaxy\",\"creatorType\":\"User\",\"totalUpVotes\":257650,\"totalDownVotes\":23838,\"universeId\":2387288336,\"name\":\"Basically FNF\",\"placeId\":6417009050,\"playerCount\":19861,\"imageToken\":\"T_6417009050_b437\",\"isSponsored\":false,\"nativeAdData\":\"\",\"isShowSponsoredLabel\":false,\"price\":null,\"analyticsIdentifier\":null,\"gameDescription\":null},{\"creatorId\":3955051,\"creatorName\":\"Foxzie's Productions\",\"creatorType\":\"Group\",\"totalUpVotes\":181290,\"totalDownVotes\":31988,\"universeId\":605887098,\"name\":\"🥚 EGG HUNT! 🐰 Car Dealership Tycoon\",\"placeId\":1554960397,\"playerCount\":26716,\"imageToken\":\"T_1554960397_43b2\",\"isSponsored\":false,\"nativeAdData\":\"\",\"isShowSponsoredLabel\":false,\"price\":null,\"analyticsIdentifier\":null,\"gameDescription\":null},{\"creatorId\":1730435200,\"creatorName\":\"SnowdustDev\",\"creatorType\":\"User\",\"totalUpVotes\":134662,\"totalDownVotes\":61022,\"universeId\":1852226622,\"name\":\"Gacha Online| Custom OC RP⭐ (Roleplay)\",\"placeId\":5289509545,\"playerCount\":29238,\"imageToken\":\"T_5289509545_1eec\",\"isSponsored\":false,\"nativeAdData\":\"\",\"isShowSponsoredLabel\":false,\"price\":null,\"analyticsIdentifier\":null,\"gameDescription\":null},{\"creatorId\":4914494,\"creatorName\":\"Paradoxum Games\",\"creatorType\":\"Group\",\"totalUpVotes\":489037,\"totalDownVotes\":40697,\"universeId\":1176784616,\"name\":\"🏆Tower Defense Simulator🏆\",\"placeId\":3260590327,\"playerCount\":12926,\"imageToken\":\"T_3260590327_d762\",\"isSponsored\":false,\"nativeAdData\":\"\",\"isShowSponsoredLabel\":false,\"price\":null,\"analyticsIdentifier\":null,\"gameDescription\":null},{\"creatorId\":4111519,\"creatorName\":\"Dev Rel Development\",\"creatorType\":\"Group\",\"totalUpVotes\":82222,\"totalDownVotes\":5880,\"universeId\":2284882312,\"name\":\"8th Annual Bloxy Awards\",\"placeId\":6225076142,\"playerCount\":14473,\"imageToken\":\"T_6225076142_990f\",\"isSponsored\":false,\"nativeAdData\":\"\",\"isShowSponsoredLabel\":false,\"price\":null,\"analyticsIdentifier\":null,\"gameDescription\":null},{\"creatorId\":4570453,\"creatorName\":\"One Piece Millennium\",\"creatorType\":\"Group\",\"totalUpVotes\":23773,\"totalDownVotes\":3575,\"universeId\":2076312981,\"name\":\"[Alpha] One Piece: Millennium 3\",\"placeId\":5835263912,\"playerCount\":8538,\"imageToken\":\"T_5835263912_252\",\"isSponsored\":false,\"nativeAdData\":\"\",\"isShowSponsoredLabel\":false,\"price\":null,\"analyticsIdentifier\":null,\"gameDescription\":null},{\"creatorId\":3229308,\"creatorName\":\"Grand Quest Games\",\"creatorType\":\"Group\",\"totalUpVotes\":110353,\"totalDownVotes\":6238,\"universeId\":648454481,\"name\":\"[2X LOGIA ❤️VALENTINE EVENT]Grand Piece Online\",\"placeId\":1730877806,\"playerCount\":6420,\"imageToken\":\"T_1730877806_428d\",\"isSponsored\":false,\"nativeAdData\":\"\",\"isShowSponsoredLabel\":false,\"price\":200,\"analyticsIdentifier\":null,\"gameDescription\":null},{\"creatorId\":6258143,\"creatorName\":\"Wonder Works Studio\",\"creatorType\":\"Group\",\"totalUpVotes\":264245,\"totalDownVotes\":43656,\"universeId\":1751969566,\"name\":\"[Egg Hunt]🐰Overlook Bay!\",\"placeId\":5063122755,\"playerCount\":19645,\"imageToken\":\"T_5063122755_b37a\",\"isSponsored\":false,\"nativeAdData\":\"\",\"isShowSponsoredLabel\":false,\"price\":null,\"analyticsIdentifier\":null,\"gameDescription\":null},{\"creatorId\":4698921,\"creatorName\":\"Da Hood Entertainment\",\"creatorType\":\"Group\",\"totalUpVotes\":236524,\"totalDownVotes\":128218,\"universeId\":1008451066,\"name\":\"Da Hood\",\"placeId\":2788229376,\"playerCount\":12744,\"imageToken\":\"T_2788229376_aeaa\",\"isSponsored\":false,\"nativeAdData\":\"\",\"isShowSponsoredLabel\":false,\"price\":null,\"analyticsIdentifier\":null,\"gameDescription\":null},{\"creatorId\":4484634,\"creatorName\":\"World // Zero\",\"creatorType\":\"Group\",\"totalUpVotes\":275791,\"totalDownVotes\":15770,\"universeId\":985731078,\"name\":\"World // Zero\",\"placeId\":2727067538,\"playerCount\":9025,\"imageToken\":\"T_2727067538_8ff2\",\"isSponsored\":false,\"nativeAdData\":\"\",\"isShowSponsoredLabel\":false,\"price\":null,\"analyticsIdentifier\":null,\"gameDescription\":null},{\"creatorId\":28603491,\"creatorName\":\"SushiWalrus\",\"creatorType\":\"User\",\"totalUpVotes\":544457,\"totalDownVotes\":56511,\"universeId\":380704901,\"name\":\"[PS ADMIN!] Ro-Ghoul [ALPHA]\",\"placeId\":914010731,\"playerCount\":5810,\"imageToken\":\"T_914010731_9b0a\",\"isSponsored\":false,\"nativeAdData\":\"\",\"isShowSponsoredLabel\":false,\"price\":null,\"analyticsIdentifier\":null,\"gameDescription\":null},{\"creatorId\":7371243,\"creatorName\":\"Ready, set, more!\",\"creatorType\":\"Group\",\"totalUpVotes\":203667,\"totalDownVotes\":11158,\"universeId\":1934249057,\"name\":\"Tropical Resort Tycoon 🌴\",\"placeId\":5534174456,\"playerCount\":19805,\"imageToken\":\"T_5534174456_abb7\",\"isSponsored\":false,\"nativeAdData\":\"\",\"isShowSponsoredLabel\":false,\"price\":null,\"analyticsIdentifier\":null,\"gameDescription\":null}],\"suggestedKeyword\":null,\"correctedKeyword\":null,\"filteredKeyword\":null,\"hasMoreRows\":true,\"nextPageExclusiveStartId\":null,\"featuredSearchUniverseId\":null,\"emphasis\":false,\"cutOffIndex\":null,\"algorithm\":\"GameSearchUsingSimilarQueryService\",\"algorithmQueryType\":\"Bucketboost\",\"suggestionAlgorithm\":\"GameSuggestions_V2\",\"relatedGames\":[]}"}